README.md
setup.py
src/pycouch/__init__.py
src/pycouch/error.py
src/pycouch/utility.py
src/pycouch/wrapper.py
src/pycouch.egg-info/PKG-INFO
src/pycouch.egg-info/SOURCES.txt
src/pycouch.egg-info/dependency_links.txt
src/pycouch.egg-info/not-zip-safe
src/pycouch.egg-info/requires.txt
src/pycouch.egg-info/top_level.txt