Metadata-Version: 1.1
Name: pycouch
Version: 2.1.2
Summary: Wrapper functions to interact with a couch DB
Home-page: https://github.com/MMSB-MOBI/pyCouch
Author: Guillaume Launay, Cecile Hilpert
Author-email: pitooon@gmail.com
License: BSD
Download-URL: https://github.com/glaunay/MMSB-MOBI/tarball/2.1
Keywords: couchDB,python
Platform: UNKNOWN
